castfit/__init__.py
castfit/py.typed
castfit-0.1.2.dist-info/licenses/LICENSE.md
castfit-0.1.2.dist-info/METADATA
castfit-0.1.2.dist-info/WHEEL
castfit-0.1.2.dist-info/top_level.txt
castfit-0.1.2.dist-info/RECORD
